zeug/__init__.py
zeug/utils.py
zeug-0.0.2.dist-info/LICENSE
zeug-0.0.2.dist-info/METADATA
zeug-0.0.2.dist-info/WHEEL
zeug-0.0.2.dist-info/top_level.txt
zeug-0.0.2.dist-info/RECORD
