Metadata-Version: 2.1
Name: zeug
Version: 0.0.2
Summary: Tools for ML
Home-page: https://github.com/trbznk/zeug
Author: Alexander Terbeznik
Author-email: alexander.terbeznik@gmail.com
License: UNKNOWN
Project-URL: Bug Tracker, https://github.com/trbznk/zeug/issues
Platform: UNKNOWN
Classifier: Programming Language :: Python :: 3
Classifier: License :: OSI Approved :: MIT License
Classifier: Operating System :: OS Independent
Requires-Python: >=3.6
License-File: LICENSE
